giskard/core/__init__.py
giskard/core/discriminated.py
giskard/core/errors.py
giskard_core-0.1.7.dist-info/METADATA
giskard_core-0.1.7.dist-info/WHEEL
giskard_core-0.1.7.dist-info/licenses/LICENSE
giskard_core-0.1.7.dist-info/RECORD
