Metadata-Version: 2.4
Name: giskard-core
Version: 0.1.7
Summary: Core shared utilities and foundational components for the Giskard library ecosystem.
License: MIT
License-File: LICENSE
Requires-Python: >=3.11
Requires-Dist: pydantic<3,>=2.11.0
